[
  {
    "id": "N3.4.1",
    "kanji": "消費者",
    "component": "",
    "hiragana": "しょうひしゃ",
    "enMeaning": "Consumer",
    "idMeaning": "Konsumen",
    "type": "Kata Benda"
  },
  {
    "id": "N3.4.2",
    "kanji": "受け取る",
    "component": "",
    "hiragana": "うけとる",
    "enMeaning": "Receive",
    "idMeaning": "Menerima",
    "type": "KK Transitif"
  },
  {
    "id": "N3.4.3",
    "kanji": "自動販売機",
    "component": "",
    "hiragana": "じどうはんばいき",
    "enMeaning": "Vending machine",
    "idMeaning": "Mesin penjual otomatis",
    "type": "Kata Benda"
  },
  {
    "id": "N3.4.4",
    "kanji": "歯科",
    "component": "",
    "hiragana": "しか",
    "enMeaning": "Dentistry / dental clinic",
    "idMeaning": "Klinik gigi",
    "type": "Kata Benda"
  },
  {
    "id": "N3.4.5",
    "kanji": "割れる",
    "component": "",
    "hiragana": "われる",
    "enMeaning": "Break / split",
    "idMeaning": "Pecah",
    "type": "KK Intransitif"
  },
  {
    "id": "N3.4.6",
    "kanji": "空港",
    "component": "",
    "hiragana": "くうこう",
    "enMeaning": "Airport",
    "idMeaning": "Bandara",
    "type": "Kata Benda"
  },
  {
    "id": "N3.4.7",
    "kanji": "降車口",
    "component": "",
    "hiragana": "こうしゃぐち",
    "enMeaning": "Exit (bus/train)",
    "idMeaning": "Pintu turun (bus/kereta)",
    "type": "Kata Benda"
  },
  {
    "id": "N3.4.8",
    "kanji": "看護師",
    "component": "",
    "hiragana": "かんごし",
    "enMeaning": "Nurse",
    "idMeaning": "Perawat",
    "type": "Kata Benda"
  },
  {
    "id": "N3.4.9",
    "kanji": "指定席",
    "component": "",
    "hiragana": "していせき",
    "enMeaning": "Reserved seat",
    "idMeaning": "Kursi pesanan",
    "type": "Kata Benda"
  },
  {
    "id": "N3.4.10",
    "kanji": "～様",
    "component": "",
    "hiragana": "～さま",
    "enMeaning": "Mr. / ms. ~ (keigo)",
    "idMeaning": "Tuan/Nyonya ~ (keigo)",
    "type": "Kata Benda"
  },
  {
    "id": "N3.4.11",
    "kanji": "表示",
    "component": "",
    "hiragana": "ひょうじ",
    "enMeaning": "Display / indication",
    "idMeaning": "Tampilan / indikasi",
    "type": "Kata Benda"
  },
  {
    "id": "N3.4.12",
    "kanji": "郵便",
    "component": "",
    "hiragana": "ゆうびん",
    "enMeaning": "Mail / postal service",
    "idMeaning": "Pos",
    "type": "Kata Benda"
  },
  {
    "id": "N3.4.13",
    "kanji": "限定",
    "component": "",
    "hiragana": "げんてい",
    "enMeaning": "Limited",
    "idMeaning": "Terbatas / eksklusif",
    "type": "Kata Benda"
  },
  {
    "id": "N3.4.14",
    "kanji": "小型",
    "component": "",
    "hiragana": "こがた",
    "enMeaning": "Small-sized / compact",
    "idMeaning": "Berukuran kecil",
    "type": "Kata Benda"
  },
  {
    "id": "N3.4.15",
    "kanji": "怪しい",
    "component": "",
    "hiragana": "あやしい",
    "enMeaning": "Suspicious",
    "idMeaning": "Mencurigakan",
    "type": "Kata Sifat い"
  },
  {
    "id": "N3.4.16",
    "kanji": "中級",
    "component": "",
    "hiragana": "ちゅうきゅう",
    "enMeaning": "Intermediate level",
    "idMeaning": "Tingkat menengah",
    "type": "Kata Benda"
  },
  {
    "id": "N3.4.17",
    "kanji": "出血",
    "component": "",
    "hiragana": "しゅっけつ",
    "enMeaning": "Bleeding",
    "idMeaning": "Perdarahan",
    "type": "Kata Benda"
  },
  {
    "id": "N3.4.18",
    "kanji": "税金",
    "component": "",
    "hiragana": "ぜいきん",
    "enMeaning": "Tax",
    "idMeaning": "Pajak",
    "type": "Kata Benda"
  },
  {
    "id": "N3.4.19",
    "kanji": "化粧",
    "component": "",
    "hiragana": "けしょう",
    "enMeaning": "Makeup",
    "idMeaning": "Rias",
    "type": "Kata Benda"
  },
  {
    "id": "N3.4.20",
    "kanji": "断水",
    "component": "斤",
    "hiragana": "だんすい",
    "enMeaning": "Water outage",
    "idMeaning": "Pemutusan suplai air",
    "type": "Kata Benda"
  },
  {
    "id": "N3.4.21",
    "kanji": "優しい",
    "component": "",
    "hiragana": "やさしい",
    "enMeaning": "Kind / gentle",
    "idMeaning": "Ramah / baik hati",
    "type": "Kata Sifat い"
  },
  {
    "id": "N3.4.22",
    "kanji": "快適",
    "component": "",
    "hiragana": "かいてき",
    "enMeaning": "Comfortable",
    "idMeaning": "Nyaman",
    "type": "Kata Sifat な"
  },
  {
    "id": "N3.4.23",
    "kanji": "移動",
    "component": "",
    "hiragana": "いどう",
    "enMeaning": "Movement",
    "idMeaning": "Pindah tempat / bergerak",
    "type": "Kata Benda"
  },
  {
    "id": "N3.4.24",
    "kanji": "回復",
    "component": "",
    "hiragana": "かいふく",
    "enMeaning": "Recovery",
    "idMeaning": "Pemulihan",
    "type": "Kata Benda"
  },
  {
    "id": "N3.4.25",
    "kanji": "自由席",
    "component": "",
    "hiragana": "じゆうせき",
    "enMeaning": "Non-reserved seat",
    "idMeaning": "Kursi tidak direservasi",
    "type": "Kata Benda"
  },
  {
    "id": "N3.4.26",
    "kanji": "鳴る",
    "component": "",
    "hiragana": "なる",
    "enMeaning": "Ringing (clock/phone)",
    "idMeaning": "Berbunyi (jam/HP)",
    "type": "KK Intransitif"
  },
  {
    "id": "N3.4.27",
    "kanji": "必死",
    "component": "",
    "hiragana": "ひっし",
    "enMeaning": "Desperate",
    "idMeaning": "Mati-matian / penuh usaha",
    "type": "Kata Sifat な"
  },
  {
    "id": "N3.4.28",
    "kanji": "骨折",
    "component": "斤",
    "hiragana": "こっせつ",
    "enMeaning": "Broken bone / fracture",
    "idMeaning": "Patah tulang",
    "type": "Kata Benda"
  },
  {
    "id": "N3.4.29",
    "kanji": "手荷物",
    "component": "",
    "hiragana": "てにもつ",
    "enMeaning": "Hand luggage / baggage",
    "idMeaning": "Barang bawaan",
    "type": "Kata Benda"
  },
  {
    "id": "N3.4.30",
    "kanji": "結ぶ",
    "component": "糸",
    "hiragana": "むすぶ",
    "enMeaning": "Tie / connect",
    "idMeaning": "Mengikat / menghubungkan",
    "type": "KK Transitif"
  },
  {
    "id": "N3.4.31",
    "kanji": "紙袋",
    "component": "",
    "hiragana": "かみぶくろ",
    "enMeaning": "Paper bag",
    "idMeaning": "Kantong kertas",
    "type": "Kata Benda"
  },
  {
    "id": "N3.4.32",
    "kanji": "夫婦",
    "component": "",
    "hiragana": "ふうふ",
    "enMeaning": "Married couple",
    "idMeaning": "Suami istri",
    "type": "Kata Benda"
  },
  {
    "id": "N3.4.33",
    "kanji": "受験",
    "component": "馬",
    "hiragana": "じゅけん",
    "enMeaning": "Entrance exam",
    "idMeaning": "Mengikuti ujian (masuk sekolah)",
    "type": "Kata Benda"
  },
  {
    "id": "N3.4.34",
    "kanji": "祝日",
    "component": "",
    "hiragana": "しゅくじつ",
    "enMeaning": "Public holiday",
    "idMeaning": "Hari libur nasional",
    "type": "Kata Benda"
  },
  {
    "id": "N3.4.35",
    "kanji": "裏返す",
    "component": "反",
    "hiragana": "うらがえす",
    "enMeaning": "Turn inside out / flip over",
    "idMeaning": "Membalik sisi",
    "type": "KK Transitif"
  },
  {
    "id": "N3.4.36",
    "kanji": "以降",
    "component": "",
    "hiragana": "いこう",
    "enMeaning": "After / from then on",
    "idMeaning": "Setelah itu",
    "type": "Kata Benda"
  },
  {
    "id": "N3.4.37",
    "kanji": "両",
    "component": "",
    "hiragana": "りょう",
    "enMeaning": "Both",
    "idMeaning": "Keduanya",
    "type": "Kata Benda"
  },
  {
    "id": "N3.4.38",
    "kanji": "伺う",
    "component": "",
    "hiragana": "うかがう",
    "enMeaning": "Visit / ask (keigo)",
    "idMeaning": "Bertanya (keigo)",
    "type": "KK Transitif"
  },
  {
    "id": "N3.4.39",
    "kanji": "公務員",
    "component": "",
    "hiragana": "こうむいん",
    "enMeaning": "Public servant",
    "idMeaning": "Pegawai negeri",
    "type": "Kata Benda"
  },
  {
    "id": "N3.4.40",
    "kanji": "救う",
    "component": "",
    "hiragana": "すくう",
    "enMeaning": "Save / rescue",
    "idMeaning": "Menyelamatkan",
    "type": "KK Transitif"
  },
  {
    "id": "N3.4.41",
    "kanji": "表す",
    "component": "",
    "hiragana": "あらわす",
    "enMeaning": "Express / represent",
    "idMeaning": "Mengungkapkan",
    "type": "KK Transitif"
  },
  {
    "id": "N3.4.42",
    "kanji": "年末",
    "component": "",
    "hiragana": "ねんまつ",
    "enMeaning": "Year end",
    "idMeaning": "Akhir tahun",
    "type": "Kata Benda"
  },
  {
    "id": "N3.4.43",
    "kanji": "右側",
    "component": "",
    "hiragana": "みぎがわ",
    "enMeaning": "Right side",
    "idMeaning": "Sisi kanan",
    "type": "Kata Benda"
  },
  {
    "id": "N3.4.44",
    "kanji": "差",
    "component": "",
    "hiragana": "さ",
    "enMeaning": "Difference",
    "idMeaning": "Perbedaan / selisih",
    "type": "Kata Benda"
  },
  {
    "id": "N3.4.45",
    "kanji": "選挙",
    "component": "",
    "hiragana": "せんきょ",
    "enMeaning": "Election",
    "idMeaning": "Pemilu",
    "type": "Kata Benda"
  },
  {
    "id": "N3.4.46",
    "kanji": "消しゴム",
    "component": "",
    "hiragana": "けしゴム",
    "enMeaning": "Eraser",
    "idMeaning": "Penghapus",
    "type": "Kata Benda"
  },
  {
    "id": "N3.4.47",
    "kanji": "睡眠",
    "component": "",
    "hiragana": "すいみん",
    "enMeaning": "Sleep (as activity)",
    "idMeaning": "Tidur (sebagai kegiatan)",
    "type": "Kata Benda"
  },
  {
    "id": "N3.4.48",
    "kanji": "風船",
    "component": "",
    "hiragana": "ふうせん",
    "enMeaning": "Balloon",
    "idMeaning": "Balon",
    "type": "Kata Benda"
  },
  {
    "id": "N3.4.49",
    "kanji": "加える",
    "component": "",
    "hiragana": "くわえる",
    "enMeaning": "Add",
    "idMeaning": "Menambahkan",
    "type": "KK Transitif"
  },
  {
    "id": "N3.4.50",
    "kanji": "数学",
    "component": "",
    "hiragana": "すうがく",
    "enMeaning": "Mathematics",
    "idMeaning": "Matematika",
    "type": "Kata Benda"
  },
  {
    "id": "N3.4.51",
    "kanji": "用件",
    "component": "",
    "hiragana": "ようけん",
    "enMeaning": "Business / matter",
    "idMeaning": "Keperluan",
    "type": "Kata Benda"
  },
  {
    "id": "N3.4.52",
    "kanji": "職場",
    "component": "",
    "hiragana": "しょくば",
    "enMeaning": "Workplace",
    "idMeaning": "Tempat kerja",
    "type": "Kata Benda"
  },
  {
    "id": "N3.4.53",
    "kanji": "死亡",
    "component": "",
    "hiragana": "しぼう",
    "enMeaning": "Death",
    "idMeaning": "Meninggal",
    "type": "Kata Benda"
  },
  {
    "id": "N3.4.54",
    "kanji": "再入国",
    "component": "玉",
    "hiragana": "さいにゅうこく",
    "enMeaning": "Re-entry (country)",
    "idMeaning": "Masuk kembali (negara)",
    "type": "Kata Benda"
  },
  {
    "id": "N3.4.55",
    "kanji": "最も",
    "component": "",
    "hiragana": "もっとも",
    "enMeaning": "Most",
    "idMeaning": "Paling",
    "type": "Kata Benda"
  },
  {
    "id": "N3.4.56",
    "kanji": "移る",
    "component": "",
    "hiragana": "うつる",
    "enMeaning": "Move / transfer",
    "idMeaning": "Pindah (tempat/posisi)",
    "type": "KK Intransitif"
  },
  {
    "id": "N3.4.57",
    "kanji": "改札口",
    "component": "",
    "hiragana": "かいさつぐち",
    "enMeaning": "Ticket gate",
    "idMeaning": "Gerbang tiket",
    "type": "Kata Benda"
  },
  {
    "id": "N3.4.58",
    "kanji": "欠ける",
    "component": "",
    "hiragana": "かける",
    "enMeaning": "Chip / be missing",
    "idMeaning": "Terpotong / tidak lengkap",
    "type": "KK Intransitif"
  },
  {
    "id": "N3.4.59",
    "kanji": "高齢",
    "component": "",
    "hiragana": "こうれい",
    "enMeaning": "Old age",
    "idMeaning": "Lanjut usia",
    "type": "Kata Benda"
  },
  {
    "id": "N3.4.60",
    "kanji": "商品",
    "component": "",
    "hiragana": "しょうひん",
    "enMeaning": "Product",
    "idMeaning": "Produk dagangan",
    "type": "Kata Benda"
  },
  {
    "id": "N3.4.61",
    "kanji": "道路",
    "component": "首",
    "hiragana": "どうろ",
    "enMeaning": "Road",
    "idMeaning": "Jalan raya",
    "type": "Kata Benda"
  },
  {
    "id": "N3.4.62",
    "kanji": "定期券",
    "component": "",
    "hiragana": "ていきけん",
    "enMeaning": "Commuter pass",
    "idMeaning": "Kartu transportasi",
    "type": "Kata Benda"
  },
  {
    "id": "N3.4.63",
    "kanji": "帯",
    "component": "",
    "hiragana": "おび",
    "enMeaning": "Belt / sash",
    "idMeaning": "Sabuk",
    "type": "Kata Benda"
  },
  {
    "id": "N3.4.64",
    "kanji": "角度",
    "component": "",
    "hiragana": "かくど",
    "enMeaning": "Angle",
    "idMeaning": "Sudut (matematika)",
    "type": "Kata Benda"
  },
  {
    "id": "N3.4.65",
    "kanji": "邪魔する",
    "component": "",
    "hiragana": "じゃまする",
    "enMeaning": "Interrupt / disturb",
    "idMeaning": "Mengganggu / menghalangi",
    "type": "KK Transitif"
  },
  {
    "id": "N3.4.66",
    "kanji": "回数券",
    "component": "",
    "hiragana": "かいすうけん",
    "enMeaning": "Coupon ticket",
    "idMeaning": "Kupon beberapa kali",
    "type": "Kata Benda"
  },
  {
    "id": "N3.4.67",
    "kanji": "汗",
    "component": "",
    "hiragana": "あせ",
    "enMeaning": "Sweat",
    "idMeaning": "Keringat",
    "type": "Kata Benda"
  },
  {
    "id": "N3.4.68",
    "kanji": "車庫",
    "component": "",
    "hiragana": "しゃこ",
    "enMeaning": "Garage",
    "idMeaning": "Garasi",
    "type": "Kata Benda"
  },
  {
    "id": "N3.4.69",
    "kanji": "～両",
    "component": "",
    "hiragana": "～りょう",
    "enMeaning": "Counter for vehicles",
    "idMeaning": "Gerbong (kereta)",
    "type": "Kata Benda"
  },
  {
    "id": "N3.4.70",
    "kanji": "～番",
    "component": "",
    "hiragana": "～ばん",
    "enMeaning": "Number / order",
    "idMeaning": "Nomor ~",
    "type": "Kata Benda"
  },
  {
    "id": "N3.4.71",
    "kanji": "差し出す",
    "component": "",
    "hiragana": "さしだす",
    "enMeaning": "Hand over / submit",
    "idMeaning": "Menyerahkan / memberikan",
    "type": "KK Transitif"
  },
  {
    "id": "N3.4.72",
    "kanji": "乗車券",
    "component": "",
    "hiragana": "じょうしゃけん",
    "enMeaning": "Commute ticket (train/bus)",
    "idMeaning": "Tiket (kereta/bus)",
    "type": "Kata Benda"
  },
  {
    "id": "N3.4.73",
    "kanji": "電波",
    "component": "雨皮",
    "hiragana": "でんぱ",
    "enMeaning": "Radio wave",
    "idMeaning": "Sinyal (radio/HP)",
    "type": "Kata Benda"
  },
  {
    "id": "N3.4.74",
    "kanji": "決まる",
    "component": "",
    "hiragana": "きまる",
    "enMeaning": "Be decided",
    "idMeaning": "Diputuskan / ditentukan",
    "type": "KK Intransitif"
  },
  {
    "id": "N3.4.75",
    "kanji": "例",
    "component": "列",
    "hiragana": "れい",
    "enMeaning": "Example",
    "idMeaning": "Contoh",
    "type": "Kata Benda"
  },
  {
    "id": "N3.4.76",
    "kanji": "昼寝",
    "component": "",
    "hiragana": "ひるね",
    "enMeaning": "Nap",
    "idMeaning": "Tidur siang",
    "type": "Kata Benda"
  },
  {
    "id": "N3.4.77",
    "kanji": "酒屋",
    "component": "",
    "hiragana": "さかや",
    "enMeaning": "Liquor store",
    "idMeaning": "Toko minuman beralkohol",
    "type": "Kata Benda"
  },
  {
    "id": "N3.4.78",
    "kanji": "頭痛",
    "component": "",
    "hiragana": "ずつう",
    "enMeaning": "Headache",
    "idMeaning": "Sakit kepala",
    "type": "Kata Benda"
  },
  {
    "id": "N3.4.79",
    "kanji": "職員",
    "component": "",
    "hiragana": "しょくいん",
    "enMeaning": "Staff",
    "idMeaning": "Staf / pegawai",
    "type": "Kata Benda"
  },
  {
    "id": "N3.4.80",
    "kanji": "配送料",
    "component": "",
    "hiragana": "はいそうりょう",
    "enMeaning": "Shipping fee",
    "idMeaning": "Ongkos kirim",
    "type": "Kata Benda"
  },
  {
    "id": "N3.4.81",
    "kanji": "感情",
    "component": "",
    "hiragana": "かんじょう",
    "enMeaning": "Emotion",
    "idMeaning": "Emosi / perasaan",
    "type": "Kata Benda"
  },
  {
    "id": "N3.4.82",
    "kanji": "ごみ袋",
    "component": "",
    "hiragana": "ごみぶくろ",
    "enMeaning": "Garbage bag",
    "idMeaning": "Kantong sampah",
    "type": "Kata Benda"
  },
  {
    "id": "N3.4.83",
    "kanji": "横断",
    "component": "斤",
    "hiragana": "おうだん",
    "enMeaning": "Crossing",
    "idMeaning": "Menyebrangi",
    "type": "Kata Benda"
  },
  {
    "id": "N3.4.84",
    "kanji": "窓口",
    "component": "",
    "hiragana": "まどぐ口",
    "enMeaning": "Counter",
    "idMeaning": "Loket pelayanan",
    "type": "Kata Benda"
  },
  {
    "id": "N3.4.85",
    "kanji": "苦労",
    "component": "",
    "hiragana": "くろう",
    "enMeaning": "Hardship",
    "idMeaning": "Kesusahan / perjuangan",
    "type": "Kata Benda"
  },
  {
    "id": "N3.4.86",
    "kanji": "泊める",
    "component": "",
    "hiragana": "とめる",
    "enMeaning": "Let stay overnight",
    "idMeaning": "Menginapkan",
    "type": "KK Transitif"
  },
  {
    "id": "N3.4.87",
    "kanji": "終了",
    "component": "",
    "hiragana": "しゅうりょう",
    "enMeaning": "End / finish",
    "idMeaning": "Selesai",
    "type": "Kata Benda"
  },
  {
    "id": "N3.4.88",
    "kanji": "冷凍庫",
    "component": "",
    "hiragana": "れいとうこ",
    "enMeaning": "Freezer",
    "idMeaning": "Freezer",
    "type": "Kata Benda"
  },
  {
    "id": "N3.4.89",
    "kanji": "選手",
    "component": "",
    "hiragana": "せんしゅ",
    "enMeaning": "Athlete / player",
    "idMeaning": "Atlet",
    "type": "Kata Benda"
  },
  {
    "id": "N3.4.90",
    "kanji": "三角形",
    "component": "",
    "hiragana": "さんかくけい",
    "enMeaning": "Triangle",
    "idMeaning": "Segitiga",
    "type": "Kata Benda"
  },
  {
    "id": "N3.4.91",
    "kanji": "実際に",
    "component": "",
    "hiragana": "じっさいに",
    "enMeaning": "Actually",
    "idMeaning": "Secara nyata / benar-benar",
    "type": "Kata Benda"
  },
  {
    "id": "N3.4.92",
    "kanji": "通勤",
    "component": "甬",
    "hiragana": "つうきん",
    "enMeaning": "Commuting",
    "idMeaning": "Pulang-pergi kerja",
    "type": "Kata Benda"
  },
  {
    "id": "N3.4.93",
    "kanji": "観客",
    "component": "見各",
    "hiragana": "かんきゃく",
    "enMeaning": "Audience / spectators",
    "idMeaning": "Penonton",
    "type": "Kata Benda"
  },
  {
    "id": "N3.4.94",
    "kanji": "食欲",
    "component": "谷欠",
    "hiragana": "しょくよく",
    "enMeaning": "Appetite",
    "idMeaning": "Nafsu makan",
    "type": "Kata Benda"
  },
  {
    "id": "N3.4.95",
    "kanji": "般",
    "component": "",
    "hiragana": "ばん",
    "enMeaning": "General",
    "idMeaning": "Umum",
    "type": "Kata Benda"
  },
  {
    "id": "N3.4.96",
    "kanji": "減らす",
    "component": "",
    "hiragana": "へらす",
    "enMeaning": "Reduce / decrease",
    "idMeaning": "Mengurangi",
    "type": "KK Transitif"
  },
  {
    "id": "N3.4.97",
    "kanji": "整形外科",
    "component": "夕",
    "hiragana": "せいけいげか",
    "enMeaning": "Orthopedics",
    "idMeaning": "Bedah ortopedi",
    "type": "Kata Benda"
  },
  {
    "id": "N3.4.98",
    "kanji": "往復",
    "component": "",
    "hiragana": "おうふく",
    "enMeaning": "Round trip",
    "idMeaning": "Pulang-pergi (PP)",
    "type": "Kata Benda"
  },
  {
    "id": "N3.4.99",
    "kanji": "新婚旅行",
    "component": "斤女方",
    "hiragana": "しんこんりょこう",
    "enMeaning": "Honeymoon",
    "idMeaning": "Bulan madu",
    "type": "Kata Benda"
  },
  {
    "id": "N3.4.100",
    "kanji": "保存する",
    "component": "",
    "hiragana": "ほぞんする",
    "enMeaning": "Save / store",
    "idMeaning": "Menyimpan",
    "type": "KK Transitif"
  }
]